odoo/addons/cooperator_website_recaptcha/README.rst
odoo/addons/cooperator_website_recaptcha/__init__.py
odoo/addons/cooperator_website_recaptcha/__manifest__.py
odoo/addons/cooperator_website_recaptcha/controllers/__init__.py
odoo/addons/cooperator_website_recaptcha/controllers/main.py
odoo/addons/cooperator_website_recaptcha/i18n/cooperator_website_recaptcha.pot
odoo/addons/cooperator_website_recaptcha/i18n/it.po
odoo/addons/cooperator_website_recaptcha/readme/CONTRIBUTORS.rst
odoo/addons/cooperator_website_recaptcha/readme/DESCRIPTION.rst
odoo/addons/cooperator_website_recaptcha/static/description/icon.png
odoo/addons/cooperator_website_recaptcha/static/description/index.html
odoo/addons/cooperator_website_recaptcha/views/subscription_template.xml
odoo_addon_cooperator_website_recaptcha-16.0.1.0.0.4.dist-info/METADATA
odoo_addon_cooperator_website_recaptcha-16.0.1.0.0.4.dist-info/WHEEL
odoo_addon_cooperator_website_recaptcha-16.0.1.0.0.4.dist-info/top_level.txt
odoo_addon_cooperator_website_recaptcha-16.0.1.0.0.4.dist-info/RECORD
